rotate_right.vhdl
library IEEE;
use IEEE.std_logic_1164.all;

entity rotate_right is
    port (
      operand_1: in std_logic_vector(7 downto 0);
      result  : out std_logic_vector(7 downto 0)
    );
end entity rotate_right;

architecture rtl of rotate_right is
begin
    process(operand_1)
    begin
        result <= operand_1(0) & operand_1(7 downto 1);  -- Rotate right by 1 bit
    end process;

end architecture rtl;

rotate_left.vhdl
library IEEE;
use IEEE.std_logic_1164.all;

entity rotate_left is
    port (
      operand_1: in std_logic_vector(7 downto 0);
      result  : out std_logic_vector(7 downto 0)
    );
end entity rotate_left;

architecture rtl of rotate_left is
begin 
    process(operand_1)
    begin
        result <= operand_1(6 downto 0) & operand_1(7);  -- Rotate left by 1 bit
    end process;

end architecture rtl;

shift_right.vhdl
library IEEE;
use IEEE.std_logic_1164.all;

entity shift_right is
    port (
      operand_1: in std_logic_vector(7 downto 0);
      result  : out std_logic_vector(7 downto 0)
    );
end entity shift_right;

architecture rtl of shift_right is
begin 
    process(operand_1)
    begin
        result <= '0' & operand_1(7 downto 1);  -- Shift right by 1 bit
    end process;

end architecture rtl;

shift_left.vhdl
library IEEE;
use IEEE.std_logic_1164.all;


entity shift_left is
    port (
      operand_1: in std_logic_vector(7 downto 0);
      result  : out std_logic_vector(7 downto 0)
    );
end entity shift_left;

architecture rtl of shift_left is
begin
    process(operand_1)
    begin
        result <= operand_1(6 downto 0) & '0';  -- Shift left by 1 bit
    end process;

end architecture rtl;

alu.vhdl
library ieee;
use ieee.std_logic_1164.all;

entity alu is
    port(
        opcode : in std_logic_vector(3 downto 0);      -- 4-bit opcode input
        operand_1 : in std_logic_vector(7 downto 0);   -- 8-bit first operand input
        operand_2 : in std_logic_vector(7 downto 0);   -- 8-bit second operand input
        result : out std_logic_vector(7 downto 0)     -- 8
    ); 
end alu;

architecture rtl of alu is
    component shift_left is
        port (
      operand_1: in std_logic_vector(7 downto 0);
      result  : out std_logic_vector(7 downto 0)
    );
    end component;
    component shift_right is
        port (
      operand_1: in std_logic_vector(7 downto 0);
      result  : out std_logic_vector(7 downto 0)
    );
    end component;
    component rotate_left is
        port (
      operand_1: in std_logic_vector(7 downto 0);
      result  : out std_logic_vector(7 downto 0)
    );
    end component;
    component rotate_right is
        port (
      operand_1: in std_logic_vector(7 downto 0);
      result  : out std_logic_vector(7 downto 0)
    );
    end component;

    signal resultSL : std_logic_vector(7 downto 0);
    signal resultSR : std_logic_vector(7 downto 0);
    signal resultRL : std_logic_vector(7 downto 0);
    signal resultRR : std_logic_vector(7 downto 0);
begin
        shift_left_module : shift_left port map (operand_1, resultSL);
        shift_right_module : shift_right port map (operand_1, resultSR);
        rotate_left_module : rotate_left port map (operand_1, resultRL);
        rotate_right_module : rotate_right port map (operand_1, resultRR);

    result <= operand_1 and operand_2 when opcode = "0000" else
        operand_1 or operand_2 when opcode = "0001" else
        not(operand_1) when opcode = "0010" else
        not(operand_2) when opcode = "0011" else
        resultSL when opcode = "0100" else
        resultSR when opcode = "0101" else
        resultRL when opcode = "0110" else
        resultRR when opcode = "0111" else
        (others => 'Z');
end rtl;

tb_alu.vhdl
library ieee;
use ieee.std_logic_1164.all;

entity tb_alu is
end tb_alu;


architecture rtl of tb_alu is
    component alu is
        port(
        opcode : in std_logic_vector(3 downto 0);      -- 4-bit opcode input
        operand_1 : in std_logic_vector(7 downto 0);   -- 8-bit first operand input
        operand_2 : in std_logic_vector(7 downto 0);   -- 8-bit second operand input
        result : out std_logic_vector(7 downto 0)
        );
    end component;

    signal tb_opcode : std_logic_vector(3 downto 0);      -- 4-bit opcode input
    signal tb_operand_1 :  std_logic_vector(7 downto 0);   -- 8-bit first operand input
    signal tb_operand_2 :  std_logic_vector(7 downto 0);   -- 8-bit second operand input
    signal tb_result :  std_logic_vector(7 downto 0);

begin 
        alu_module : alu port map (tb_opcode, tb_operand_1, tb_operand_2, tb_result);

    process
        begin
        tb_opcode <= "0000";
        tb_operand_1 <= "00111010";
        tb_operand_2 <= "10111001";
        wait for 10 ms;
            
        tb_opcode <= "0001";
        
        wait for 10 ms;
    
        tb_opcode <= "0010";
        
        wait for 10 ms;

        tb_opcode <= "0011";
        
        wait for 10 ms;

        tb_opcode <= "0100";
        
        wait for 10 ms;

        tb_opcode <= "0101";
        
        wait for 10 ms;

        tb_opcode <= "0110";
        
        wait for 10 ms;

        tb_opcode <= "0111";
        
        wait for 10 ms;
               
        wait;
    
    end process;

end rtl;

alu_wav.vcd
$date
  Thu Aug 14 16:17:11 2025
$end
$version
  GHDL v0
$end
$timescale
  1 fs
$end
$scope module standard $end
$upscope $end
$scope module std_logic_1164 $end
$upscope $end
$scope module tb_alu $end
$var reg 4 ! tb_opcode[3:0] $end
$var reg 8 " tb_operand_1[7:0] $end
$var reg 8 # tb_operand_2[7:0] $end
$var reg 8 $ tb_result[7:0] $end
$scope module alu_module $end
$var reg 4 % opcode[3:0] $end
$var reg 8 & operand_1[7:0] $end
$var reg 8 ' operand_2[7:0] $end
$var reg 8 ( result[7:0] $end
$var reg 8 ) resultsl[7:0] $end
$var reg 8 * resultsr[7:0] $end
$var reg 8 + resultrl[7:0] $end
$var reg 8 , resultrr[7:0] $end
$scope module shift_left_module $end
$var reg 8 - operand_1[7:0] $end
$var reg 8 . result[7:0] $end
$upscope $end
$scope module shift_right_module $end
$var reg 8 / operand_1[7:0] $end
$var reg 8 0 result[7:0] $end
$upscope $end
$scope module rotate_left_module $end
$var reg 8 1 operand_1[7:0] $end
$var reg 8 2 result[7:0] $end
$upscope $end
$scope module rotate_right_module $end
$var reg 8 3 operand_1[7:0] $end
$var reg 8 4 result[7:0] $end
$upscope $end
$upscope $end
$upscope $end
$enddefinitions $end
#0
b0000 !
b00111010 "
b10111001 #
b00111000 $
b0000 %
b00111010 &
b10111001 '
b00111000 (
b01110100 )
b00011101 *
b01110100 +
b00011101 ,
b00111010 -
b01110100 .
b00111010 /
b00011101 0
b00111010 1
b01110100 2
b00111010 3
b00011101 4
#10000000000000
b0001 !
b10111011 $
b0001 %
b10111011 (
#20000000000000
b0010 !
b11000101 $
b0010 %
b11000101 (
#30000000000000
b0011 !
b01000110 $
b0011 %
b01000110 (
#40000000000000
b0100 !
b01110100 $
b0100 %
b01110100 (
#50000000000000
b0101 !
b00011101 $
b0101 %
b00011101 (
#60000000000000
b0110 !
b01110100 $
b0110 %
b01110100 (
#70000000000000
b0111 !
b00011101 $
b0111 %
b00011101 (
