Decoder_74139.vhdl
library ieee;
use ieee.std_logic_1164.all;

entity decoder_74139 is
    port(
        G1 : in std_logic; 
        A, B : in std_logic;
        Y0, Y1, Y2, Y3 : out std_logic
    );
end decoder_74139;

architecture rtl of decoder_74139 is
begin
    
    Y0 <= (not(A) and not(B)) and G1;
    Y1 <= (not(A) and B) and G1;
    Y2 <= (A and not(B)) and G1;
    Y3 <= (A and B) and G1;
end rtl;

tb_Decoder_74139.vhdl
library ieee;
use ieee.std_logic_1164.all;

entity tb_decoder_74139 is
end tb_decoder_74139;

architecture rtl of tb_decoder_74139 is
    component decoder_74139 is
        port(
            G1 : in std_logic;
            A, B : in std_logic;
            Y0, Y1, Y2, Y3 : out std_logic
        );
    end component;

    signal G1 : std_logic := '0';
    signal A, B : std_logic := '0';
    signal Y0, Y1, Y2, Y3 : std_logic;

begin
    -- Instantiate the decoder
    uut: decoder_74139 port map (
        G1 => G1,
        A => A,
        B => B,
        Y0 => Y0,
        Y1 => Y1,
        Y2 => Y2,
        Y3 => Y3
    );

    -- Stimulus process
    process
    begin
        -- Initialize all signals
        G1 <= '0';
        A <= '0';
        B <= '0';
        wait for 10 ns;

        -- Enable decoder and test all input combinations manually
        G1 <= '1';
        A <= '0'; B <= '0'; wait for 10 ns;
        A <= '0'; B <= '1'; wait for 10 ns;
        A <= '1'; B <= '0'; wait for 10 ns;
        A <= '1'; B <= '1'; wait for 10 ns;

        -- Disable decoder and check outputs
        G1 <= '0';
        A <= '0'; B <= '0'; wait for 10 ns;
        A <= '0'; B <= '1'; wait for 10 ns;
        A <= '1'; B <= '0'; wait for 10 ns;
        A <= '1'; B <= '1'; wait for 10 ns;

        wait;
    end process;
end rtl;

Decoder_74139_wav.vcd
$date
  Thu Oct 09 15:34:20 2025
$end
$version
  GHDL v0
$end
$timescale
  1 fs
$end
$scope module standard $end
$upscope $end
$scope module std_logic_1164 $end
$upscope $end
$scope module tb_decoder_74139 $end
$var reg 1 ! g1 $end
$var reg 1 " a $end
$var reg 1 # b $end
$var reg 1 $ y0 $end
$var reg 1 % y1 $end
$var reg 1 & y2 $end
$var reg 1 ' y3 $end
$scope module uut $end
$var reg 1 ( g1 $end
$var reg 1 ) a $end
$var reg 1 * b $end
$var reg 1 + y0 $end
$var reg 1 , y1 $end
$var reg 1 - y2 $end
$var reg 1 . y3 $end
$upscope $end
$upscope $end
$enddefinitions $end
#0
0!
0"
0#
0$
0%
0&
0'
0(
0)
0*
0+
0,
0-
0.
#10000000
1!
1$
1(
1+
#20000000
1#
0$
1%
1*
0+
1,
#30000000
1"
0#
0%
1&
1)
0*
0,
1-
#40000000
1#
0&
1'
1*
0-
1.
#50000000
0!
0"
0#
0'
0(
0)
0*
0.
#60000000
1#
1*
#70000000
1"
0#
1)
0*
#80000000
1#
1*
