traffic_light_controller.vhdl
library ieee;
use ieee.std_logic_1164.all;

entity traffic_light_controller is
    port(
        x : in std_logic_vector (2 downto 0);
        gyr : out std_logic_vector (5 downto 0)
    );
    end traffic_light_controller;

architecture rtl of traffic_light_controller is
    begin
        with x select
            gyr <= "100001" when "000",
                "010001" when "001",
                "001100" when "010",
                "001010" when "011",
                "001100" when "100",
                "XXXXXX" when others;
    end rtl;

tb_traffic_light_controller.vhdl
library ieee;
use ieee.std_logic_1164.all;

entity tb_traffic_light_controller is
    end tb_traffic_light_controller;

architecture rtl of tb_traffic_light_controller is
    component traffic_light_controller is
        port(
        x : in std_logic_vector (2 downto 0);
        gyr : out std_logic_vector (5 downto 0)
    );
    end component;

    signal tb_x : std_logic_vector(2 downto 0);
    signal tb_gyr : std_logic_vector (5 downto 0);

begin 
        traffic_light_controller_module : traffic_light_controller port map (tb_x,tb_gyr);

        process
            begin
                tb_x <= "000";
                wait for 10 ms;
                tb_x <= "001";
                wait for 10 ms;
                tb_x <= "010";
                wait for 10 ms;
                tb_x <= "011";
                wait for 10 ms;
                tb_x <= "100";
                wait for 10 ms;
                tb_x <= "101";
                wait for 10 ms;
                tb_x <= "110";
                wait for 10 ms;
                tb_x <= "111";
                wait for 10 ms;
            wait;
        end process;

end rtl;

traffic_light_contrller_wav.vcd
$date
  Thu Aug 07 14:49:26 2025
$end
$version
  GHDL v0
$end
$timescale
  1 fs
$end
$scope module standard $end
$upscope $end
$scope module std_logic_1164 $end
$upscope $end
$scope module tb_traffic_light_controller $end
$var reg 3 ! tb_x[2:0] $end
$var reg 6 " tb_gyr[5:0] $end
$scope module traffic_light_controller_module $end
$var reg 3 # x[2:0] $end
$var reg 6 $ gyr[5:0] $end
$upscope $end
$upscope $end
$enddefinitions $end
#0
b000 !
b100001 "
b000 #
b100001 $
#10000000000000
b001 !
b010001 "
b001 #
b010001 $
#20000000000000
b010 !
b001100 "
b010 #
b001100 $
#30000000000000
b011 !
b001010 "
b011 #
b001010 $
#40000000000000
b100 !
b001100 "
b100 #
b001100 $
#50000000000000
b101 !
bXXXXXX "
b101 #
bXXXXXX $
#60000000000000
b110 !
b110 #
#70000000000000
b111 !
b111 #
